docupy/__init__.py
docupy/markdown.py
samdown/__init__.py
samdown/block.py
samdown/raw.py
docupy-0.3.2.dist-info/LICENSE
docupy-0.3.2.dist-info/METADATA
docupy-0.3.2.dist-info/WHEEL
docupy-0.3.2.dist-info/top_level.txt
docupy-0.3.2.dist-info/RECORD
