Metadata-Version: 2.1
Name: docupy
Version: 0.3.2
Summary: A markdown library.
Home-page: https://docupy.samireland.com
Author: Sam Ireland
Author-email: mail@samireland.com
License: MIT
Keywords: markdown html
Platform: UNKNOWN
Classifier: Development Status :: 4 - Beta
Classifier: Intended Audience :: Developers
Classifier: License :: OSI Approved :: MIT License
Classifier: Topic :: Text Processing :: Markup :: HTML
Classifier: Programming Language :: Python :: 3
Classifier: Programming Language :: Python :: 3.5
Classifier: Programming Language :: Python :: 3.6
Classifier: Programming Language :: Python :: 3.7
